odoo/addons/l10n_fr_ecotaxe_sale/README.rst
odoo/addons/l10n_fr_ecotaxe_sale/__init__.py
odoo/addons/l10n_fr_ecotaxe_sale/__manifest__.py
odoo/addons/l10n_fr_ecotaxe_sale/i18n/fr.po
odoo/addons/l10n_fr_ecotaxe_sale/i18n/l10n_fr_ecotaxe_sale.pot
odoo/addons/l10n_fr_ecotaxe_sale/models/__init__.py
odoo/addons/l10n_fr_ecotaxe_sale/models/sale.py
odoo/addons/l10n_fr_ecotaxe_sale/readme/CONTRIBUTORS.rst
odoo/addons/l10n_fr_ecotaxe_sale/readme/DESCRIPTION.rst
odoo/addons/l10n_fr_ecotaxe_sale/static/description/icon.png
odoo/addons/l10n_fr_ecotaxe_sale/static/description/index.html
odoo/addons/l10n_fr_ecotaxe_sale/tests/__init__.py
odoo/addons/l10n_fr_ecotaxe_sale/tests/test_sale_ecotaxe.py
odoo/addons/l10n_fr_ecotaxe_sale/views/sale_view.xml
odoo_addon_l10n_fr_ecotaxe_sale-15.0.1.0.0.4.dist-info/METADATA
odoo_addon_l10n_fr_ecotaxe_sale-15.0.1.0.0.4.dist-info/WHEEL
odoo_addon_l10n_fr_ecotaxe_sale-15.0.1.0.0.4.dist-info/top_level.txt
odoo_addon_l10n_fr_ecotaxe_sale-15.0.1.0.0.4.dist-info/RECORD
